nglpy-1.1.7.dist-info/top_level.txt
nglpy-1.1.7.dist-info/METADATA
nglpy-1.1.7.dist-info/LICENSE
nglpy-1.1.7.dist-info/RECORD
nglpy-1.1.7.dist-info/WHEEL
nglpy/ngl.py
nglpy/EmptyRegionGraph.py
nglpy/PrebuiltGraph.py
nglpy/_ngl.cpython-310-x86_64-linux-gnu.so
nglpy/__init__.py
nglpy/utils.py
nglpy/tests/test_bskeleton.py
nglpy/tests/test_prebuilt.py
nglpy/tests/__init__.py
nglpy/tests/test_utils.py
nglpy.libs/libgcc_s-a04fdf82.so.1
nglpy.libs/libstdc++-a9383cce.so.6.0.28
