Metadata-Version: 2.1
Name: nglpy
Version: 1.1.7
Summary: A wrapper library for exposing the C++ neighborhood graph library (NGL) for computing empty region graphs to python
Author-email: Dan Maljovec <maljovec002@gmail.com>
Project-URL: Documentation, https://nglpy.readthedocs.io/en/latest/
Project-URL: Source, https://github.com/maljovec/nglpy
Keywords: geometry,neighborhood,empty region graph,neighborhood graph library,beta skeleton,relative neighbor,Gabriel graph
Classifier: Development Status :: 3 - Alpha
Classifier: Intended Audience :: Science/Research
Classifier: License :: OSI Approved :: BSD License
Classifier: Programming Language :: C++
Classifier: Programming Language :: Python :: 3
Classifier: Topic :: Scientific/Engineering :: Mathematics
Requires-Python: >=2.7, <4
License-File: LICENSE
Requires-Dist: scipy
Requires-Dist: numpy
Requires-Dist: scikit-learn
Requires-Dist: pyDOE
Requires-Dist: ghalton (<0.6.2)
